Signal_Analysis/Signal_Analysis.py
Signal_Analysis/__init__.py
Signal_Analysis/features/__init__.py
Signal_Analysis/features/signal.py
Signal_Analysis-0.1.16.dist-info/DESCRIPTION.rst
Signal_Analysis-0.1.16.dist-info/METADATA
Signal_Analysis-0.1.16.dist-info/RECORD
Signal_Analysis-0.1.16.dist-info/WHEEL
Signal_Analysis-0.1.16.dist-info/metadata.json
Signal_Analysis-0.1.16.dist-info/top_level.txt
