Metadata-Version: 2.0
Name: Signal-Analysis
Version: 0.1.16
Summary: Determines different characteristics of signals.
Home-page: https://github.com/brookemosby/Speech_Analysis
Author: Brooke V Mosby
Author-email: brooke.mosby.byu@gmail.com
License: MIT
Requires-Dist: numpy
Requires-Dist: peakutils
